benchmark_keeper/__init__.py
benchmark_keeper/__main__.py
benchmark_keeper/aggregator.py
benchmark_keeper/cmd/__init__.py
benchmark_keeper/cmd/benchmark_cmd.py
benchmark_keeper/cmd/init_cmd.py
benchmark_keeper/cmd/list_cmd.py
benchmark_keeper/cmd/switch_cmd.py
benchmark_keeper/git.py
benchmark_keeper/report.py
benchmark_keeper-0.1.1.dist-info/LICENSE
benchmark_keeper-0.1.1.dist-info/METADATA
benchmark_keeper-0.1.1.dist-info/WHEEL
benchmark_keeper-0.1.1.dist-info/entry_points.txt
benchmark_keeper-0.1.1.dist-info/RECORD
